CHANGES.txt
LICENSE.txt
MANIFEST.in
README.txt
TODO.txt
bootstrap.py
buildout.cfg
setup.py
src/p01/__init__.py
src/p01.fsfile.egg-info/PKG-INFO
src/p01.fsfile.egg-info/SOURCES.txt
src/p01.fsfile.egg-info/dependency_links.txt
src/p01.fsfile.egg-info/namespace_packages.txt
src/p01.fsfile.egg-info/not-zip-safe
src/p01.fsfile.egg-info/requires.txt
src/p01.fsfile.egg-info/top_level.txt
src/p01/fsfile/README.txt
src/p01/fsfile/__init__.py
src/p01/fsfile/browser.py
src/p01/fsfile/browser.zcml
src/p01/fsfile/configure.zcml
src/p01/fsfile/exceptions.py
src/p01/fsfile/file.py
src/p01/fsfile/ghost.py
src/p01/fsfile/interfaces.py
src/p01/fsfile/openfile_windows.txt
src/p01/fsfile/schema.py
src/p01/fsfile/storage.py
src/p01/fsfile/testing.py
src/p01/fsfile/tests.py
src/p01/fsfile/tm.py
src/p01/fsfile/wsgi.py
src/p01/fsfile/generations/__init__.py
src/p01/fsfile/generations/configure.zcml