Metadata-Version: 2.1
Name: p01.fsfile
Version: 0.7.2
Summary: File system file storage base concept for Zope3
Home-page: http://pypi.python.org/pypi/p01.fsfile
Author: Roger Ineichen, Projekt01 GmbH
Author-email: dev@projekt01.ch
License: ZPL 2.1
Keywords: Zope3 z3c p01 file system storage distributed file network storage MogileFS
Platform: UNKNOWN
Classifier: Development Status :: 4 - Beta
Classifier: Environment :: Web Environment
Classifier: Intended Audience :: Developers
Classifier: License :: OSI Approved :: Zope Public License
Classifier: Programming Language :: Python
Classifier: Natural Language :: English
Classifier: Operating System :: OS Independent
Classifier: Topic :: Internet :: WWW/HTTP
Classifier: Framework :: Zope3
Provides-Extra: test
